<?xml version="1.0"?>
<Language name="asm" ext="asm">
  <Attribute Name="variable" ForeCol="#FF0000"></Attribute>
  <Identifiers CharsStart= "A..Za..z_" Content = "A..Za..z0..9_"> 
    <Keyword>
	adc add and bit call ccf cp cpd cpdr cpi cpir cpl daa dec di djnz ei ex exx
    halt im in inc ind indr ini inir jp jr ld ldd lddr ldi ldir neg nop or otdr
	otir out outd outi pop push res ret reti retn rl rla rlc rlca rld rr rra rrc
	rrca rrd rst sbc scf set sla sra srl sub xor
    </Keyword>
    <variable>a b c d e f h l i r ixh ixl iyh iyl af bc hl pc sp ix iy
	</variable>
  </Identifiers>   
   <Comment Start=";" ></Comment>
   <Token CharsStart="0..9" Content = '0..9.abcdef' Attribute='NUMBER'> </Token>  
  <Block>
    <Start> SEGMENT </Start>
	<End> ENDS </End>
  </Block>
 
</Language>
